{
  "timestamp": "2026-01-30T21:27:21.288500",
  "world_data": [
    {
      "sku": "MSFT",
      "quantity": 0,
      "confidence": 0.95,
      "source": "primary_api",
      "timestamp": "2026-01-30 21:27:21.278522",
      "metadata": {
        "price": 427.2300109863281,
        "fetched_at": "2026-01-30T21:27:21.278524",
        "source_detail": "yfinance"
      },
      "quality": "valid",
      "validation_issues": []
    }
  ],
  "active_hypotheses": [
    {
      "sku": "MSFT",
      "action": "buy",
      "reasoning": "Stock level (0) is below safety threshold (10). Risk of stockout.",
      "confidence": 1.0
    }
  ],
  "health_metrics": {
    "processed_count": 1,
    "last_action": "execution_complete"
  }
}